fintech_fraud_dao_hashing/__init__.py
fintech_fraud_dao_hashing/fintech_fraud_dao_hashing.py
fintech_fraud_dao_hashing-0.2.0.dist-info/WHEEL
fintech_fraud_dao_hashing-0.2.0.dist-info/METADATA
fintech_fraud_dao_hashing-0.2.0.dist-info/RECORD
