Metadata-Version: 2.1
Name: fintech-fraud-dao-hashing
Version: 0.2.0
Summary: 
Author: Ben Walton
Author-email: ben@unit21.ai
Requires-Python: >=3.8,<4.0
Classifier: Programming Language :: Python :: 3
Classifier: Programming Language :: Python :: 3.8
Classifier: Programming Language :: Python :: 3.9
Classifier: Programming Language :: Python :: 3.10
Requires-Dist: bitarray (>=2.5.1,<3.0.0)
Requires-Dist: mmh3 (>=3.0.0,<4.0.0)
